MANIFEST.in
README.rst
requirements.txt
setup.py
ec2_simple_snapshot.egg-info/PKG-INFO
ec2_simple_snapshot.egg-info/SOURCES.txt
ec2_simple_snapshot.egg-info/dependency_links.txt
ec2_simple_snapshot.egg-info/entry_points.txt
ec2_simple_snapshot.egg-info/requires.txt
ec2_simple_snapshot.egg-info/top_level.txt
simplesnapshot/__init__.py
simplesnapshot/cmdline.py
simplesnapshot/snapshot.py