Metadata-Version: 1.1
Name: ec2-simple-snapshot
Version: 1.0.1
Summary: A tool to make EC2 snapshot manipulation easier.
Home-page: http://github.com/nickryand/ec2-simple-snapshot
Author: Nick Downs
Author-email: nickryand@gmail.com
License: Apache 2.0
Platform: Posix; MacOS X
Classifier: Development Status :: 5 - Production/Stable
Classifier: Intended Audience :: Developers
Classifier: Intended Audience :: System Administrators
Classifier: Natural Language :: English
Classifier: License :: OSI Approved :: Apache Software License
Classifier: Programming Language :: Python
Classifier: Programming Language :: Python :: 2.7
